README
setup.py
heresafe/__init__.py
heresafe/heresafe.py
heresafe.egg-info/PKG-INFO
heresafe.egg-info/SOURCES.txt
heresafe.egg-info/dependency_links.txt
heresafe.egg-info/entry_points.txt
heresafe.egg-info/requires.txt
heresafe.egg-info/top_level.txt